RiksdagenDataDownloader/__init__.py
RiksdagenDataDownloader/api.py
RiksdagenDataDownloader/cli.py
RiksdagenDataDownloader/riksdagen_client.py
RiksdagenDataDownloader/unzip.py
RiksdagenDataDownloader-0.5.dist-info/METADATA
RiksdagenDataDownloader-0.5.dist-info/WHEEL
RiksdagenDataDownloader-0.5.dist-info/entry_points.txt
RiksdagenDataDownloader-0.5.dist-info/top_level.txt
RiksdagenDataDownloader-0.5.dist-info/RECORD
