Metadata-Version: 2.1
Name: RiksdagenDataDownloader
Version: 0.5
Summary: A tool to download data from data.riksdagen.se
Home-page: https://github.com/rickardlofberg/RiksdagenDataDownloader
Author: Rickard Lofberg
Author-email: lofberg.rickard@gmail.com
License: MIT
Platform: UNKNOWN
Classifier: License :: OSI Approved :: MIT License
Classifier: Programming Language :: Python
Classifier: Programming Language :: Python :: 3
Classifier: Programming Language :: Python :: 3.6
Classifier: Programming Language :: Python :: Implementation :: CPython
Classifier: Programming Language :: Python :: Implementation :: PyPy
Requires-Python: >=3.6.0
Requires-Dist: requests
Requires-Dist: xmltodict
